CHANGES.txt
MANIFEST.in
README.txt
run_tests.py
setup.py
test_images.py
Shake_Images.egg-info/PKG-INFO
Shake_Images.egg-info/SOURCES.txt
Shake_Images.egg-info/dependency_links.txt
Shake_Images.egg-info/not-zip-safe
Shake_Images.egg-info/requires.txt
Shake_Images.egg-info/top_level.txt
docs/README.txt
shake_images/__init__.py