Metadata-Version: 1.0
Name: Shake-Images
Version: 0.3
Summary: Simple front end to the smtplib and email modules, to simplify sending emails in your Shake app.
Home-page: http://github.com/lucuma/Shake-Mail
Author: Juan-Pablo Scaletti
Author-email: juanpablo@lucumalabs.com
License: MIT license (http://www.opensource.org/licenses/mit-license.php)
Platform: UNKNOWN
Classifier: Development Status :: 4 - Beta
Classifier: Environment :: Web Environment
Classifier: Intended Audience :: Developers
Classifier: License :: OSI Approved :: MIT License
Classifier: Operating System :: OS Independent
Classifier: Programming Language :: Python
Classifier: Topic :: Internet :: WWW/HTTP :: Dynamic Content
Classifier: Topic :: Software Development :: Libraries :: Python Modules
